tradingview_ta/__init__.py
tradingview_ta/main.py
tradingview_ta/technicals.py
tradingview_ta-3.2.10.dist-info/LICENSE
tradingview_ta-3.2.10.dist-info/METADATA
tradingview_ta-3.2.10.dist-info/WHEEL
tradingview_ta-3.2.10.dist-info/top_level.txt
tradingview_ta-3.2.10.dist-info/RECORD
