Metadata-Version: 2.1
Name: tradingview-ta
Version: 3.2.10
Summary: Unofficial TradingView technical analysis API wrapper.
Home-page: https://github.com/brian-the-dev/python-tradingview-ta
Author: Brian
Author-email: brian@brianthe.dev
License: UNKNOWN
Project-URL: Demo, https://tradingview.brianthe.dev
Project-URL: Documentation, https://python-tradingview-ta.readthedocs.io
Project-URL: Source, https://github.com/brian-the-dev/python-tradingview-ta
Platform: UNKNOWN
Classifier: Programming Language :: Python :: 3
Classifier: License :: OSI Approved :: MIT License
Classifier: Operating System :: OS Independent
Requires-Python: >=3.6
License-File: LICENSE
